setup.py
common/__init__.py
deomo_py.egg-info/PKG-INFO
deomo_py.egg-info/SOURCES.txt
deomo_py.egg-info/dependency_links.txt
deomo_py.egg-info/top_level.txt