Metadata-Version: 1.1
Name: deomo-py
Version: 1.0.0.dev1
Summary: A hive client python project
Home-page: https://github.com/calvinjiang/hive-executor-py
Author: Calvin Jiang
Author-email: jianghuachinacom@163.com
License: MIT
Keywords: hive client python
Platform: UNKNOWN
Classifier: Development Status :: 4 - Beta
Classifier: Intended Audience :: Developers
Classifier: Topic :: Software Development :: Build Tools
Classifier: License :: OSI Approved :: MIT License
Classifier: Programming Language :: Python :: 2.6
Classifier: Programming Language :: Python :: 2.7
Classifier: Programming Language :: Python :: 3
Classifier: Programming Language :: Python :: 3.3
Classifier: Programming Language :: Python :: 3.4
Classifier: Programming Language :: Python :: 3.5
